MANIFEST.in
README.md
setup.cfg
setup.py
codalab_yaml_validator/__init__.py
codalab_yaml_validator/schema.yaml
codalab_yaml_validator/yaml_validator.py
codalab_yaml_validator.egg-info/PKG-INFO
codalab_yaml_validator.egg-info/SOURCES.txt
codalab_yaml_validator.egg-info/dependency_links.txt
codalab_yaml_validator.egg-info/entry_points.txt
codalab_yaml_validator.egg-info/requires.txt
codalab_yaml_validator.egg-info/top_level.txt