Metadata-Version: 2.1
Name: codalab-yaml-validator
Version: 0.0.9
Summary: UNKNOWN
Home-page: https://github.com/codalab/codalab-bundle-validator
License: MIT
Platform: UNKNOWN
Requires-Python: >=3
